kabaret/__init__.py
kabaret/ingrid/__init__.py
kabaret/ingrid/demo_flow.py
kabaret/ingrid/flow_objects.py
kabaret/ingrid/ingrid_view.py
kabaret.ingrid-0.0.0a4.dist-info/METADATA
kabaret.ingrid-0.0.0a4.dist-info/RECORD
kabaret.ingrid-0.0.0a4.dist-info/WHEEL
kabaret.ingrid-0.0.0a4.dist-info/top_level.txt
