Metadata-Version: 2.1
Name: kabaret.ingrid
Version: 0.0.0a4
Summary: A Grid/Table view for the Kabaret framework flow objects
Home-page: https://gitlab.com/kabaretstudio/kabaret.ingrid
Author: Damien "dee" Coureau
Author-email: kabaret-dev@googlegroups.com
License: LGPLv3+
Keywords: kabaret vfx animation spreadsheet pipeline dataflow workflow asset manager
Platform: UNKNOWN
Classifier: Development Status :: 2 - Pre-Alpha
Classifier: Topic :: Office/Business
Classifier: Topic :: Office/Business :: Financial :: Spreadsheet
Classifier: Intended Audience :: Developers
Classifier: Intended Audience :: End Users/Desktop
Classifier: Operating System :: OS Independent
Classifier: Programming Language :: Python :: 2.7
Classifier: Programming Language :: Python :: 3.3
Classifier: License :: OSI Approved :: GNU Lesser General Public License v3 or later (LGPLv3+)
Requires-Python: >=2.7,!=3.0.*,!=3.1.*,!=3.2.*
Requires-Dist: kabaret (>=2.1.1)
